database_mysql_local/__init__.py
database_mysql_local/connector.py
database_mysql_local/constants_src.py
database_mysql_local/copy_table.py
database_mysql_local/cursor.py
database_mysql_local/delete_test_data.py
database_mysql_local/generate_table_columns.py
database_mysql_local/generic_crud.py
database_mysql_local/generic_crud_ml.py
database_mysql_local/generic_crud_mysql.py
database_mysql_local/generic_mapping.py
database_mysql_local/point.py
database_mysql_local/polygon.py
database_mysql_local/sync_conflict_resolution.py
database_mysql_local/table_columns.py
database_mysql_local/table_definition.py
database_mysql_local/test_mysql_object.py
database_mysql_local/to_sql_interface.py
database_mysql_local/utils.py
database_mysql_local/version.py
database_mysql_local-0.1.51.dist-info/licenses/LICENSE
database_mysql_local-0.1.51.dist-info/METADATA
database_mysql_local-0.1.51.dist-info/WHEEL
database_mysql_local-0.1.51.dist-info/top_level.txt
database_mysql_local-0.1.51.dist-info/RECORD
